readme_md/__init__.py
readme_md/broken_links.py
readme_md/create.py
readme_md/links.py
readme_md/tables.py
readme_md-2019.1.28.dist-info/METADATA
readme_md-2019.1.28.dist-info/WHEEL
readme_md-2019.1.28.dist-info/top_level.txt
readme_md-2019.1.28.dist-info/RECORD
