Metadata-Version: 2.1
Name: readme-md
Version: 2019.1.28
Summary: README.md generator
Home-page: https://github.com/looking-for-a-job/readme-md.py
License: UNKNOWN
Keywords: readme markdown
Platform: UNKNOWN
Classifier: License :: Public Domain
Classifier: Operating System :: OS Independent
Classifier: Programming Language :: Python
Classifier: Programming Language :: Python :: 2.7
Classifier: Programming Language :: Python :: 3.4
Classifier: Programming Language :: Python :: 3.5
Classifier: Programming Language :: Python :: 3.6
Classifier: Programming Language :: Python :: 3.7
Classifier: Topic :: Documentation
Classifier: Topic :: Software Development :: Documentation
